{
  "sites": [
    {
      "id": "4f6fdb89-bbfd-4404-a8e9-89059587f755",
      "key": "无尽资源",
      "name": "无尽资源",
      "api": "https://api.wujinapi.com/api.php/provide/vod",
      "type": 2,
      "isActive": 1,
      "time": "2026-07-05T08:40:14.167Z",
      "isDefault": 0,
      "remark": "speed:54ms",
      "tags": [],
      "priority": 0,
      "proxyMode": "none",
      "customProxy": ""
    },
    {
      "id": "6b6db9c7-2ba8-4b48-959a-19310d2c6653",
      "key": "光速HTTP",
      "name": "光速HTTP",
      "api": "http://api.guangsuapi.com/api.php/provide/vod",
      "type": 2,
      "isActive": 1,
      "time": "2026-07-05T08:40:14.168Z",
      "isDefault": 0,
      "remark": "speed:56ms",
      "tags": [],
      "priority": 0,
      "proxyMode": "none",
      "customProxy": ""
    },
    {
      "id": "938019ad-7a8d-4e8d-8a15-36da17b8885e",
      "key": "步步高资源",
      "name": "步步高资源",
      "api": "https://api.yparse.com/api/json",
      "type": 2,
      "isActive": 1,
      "time": "2026-07-05T08:40:14.168Z",
      "isDefault": 0,
      "remark": "speed:63ms",
      "tags": [],
      "priority": 0,
      "proxyMode": "none",
      "customProxy": ""
    },
    {
      "id": "efe19ab6-5ab3-400a-8a95-aab7e5db0f1d",
      "key": "爱蛋资源",
      "name": "爱蛋资源",
      "api": "https://lovedan.net/api.php/provide/vod",
      "type": 2,
      "isActive": 1,
      "time": "2026-07-05T08:40:14.168Z",
      "isDefault": 0,
      "remark": "speed:66ms",
      "tags": [],
      "priority": 0,
      "proxyMode": "none",
      "customProxy": ""
    },
    {
      "id": "7f554aa8-5b5d-4934-a430-54909fe15559",
      "key": "金鹰点播",
      "name": "金鹰点播",
      "api": "https://jinyingzy.com/api.php/provide/vod",
      "type": 2,
      "isActive": 1,
      "time": "2026-07-05T08:40:14.168Z",
      "isDefault": 0,
      "remark": "speed:73ms",
      "tags": [],
      "priority": 0,
      "proxyMode": "none",
      "customProxy": ""
    },
    {
      "id": "3c209f5c-2046-41c0-bbbb-c24b82921d3d",
      "key": "155",
      "name": "155",
      "api": "https://155api.com/api.php/provide/vod",
      "type": 2,
      "isActive": 1,
      "time": "2026-07-05T08:40:14.168Z",
      "isDefault": 0,
      "remark": "speed:79ms",
      "tags": [],
      "priority": 0,
      "proxyMode": "none",
      "customProxy": ""
    },
    {
      "id": "89745a67-a1c1-406f-8d0c-0efb5333c2b3",
      "key": "无尽ME",
      "name": "无尽ME",
      "api": "https://api.wujinapi.me/api.php/provide/vod",
      "type": 2,
      "isActive": 1,
      "time": "2026-07-05T08:40:14.168Z",
      "isDefault": 0,
      "remark": "speed:80ms",
      "tags": [],
      "priority": 0,
      "proxyMode": "none",
      "customProxy": ""
    },
    {
      "id": "ac5bd2cd-c99b-4c01-a857-f91ff4fb6479",
      "key": "索尼资源",
      "name": "索尼资源",
      "api": "https://suoniapi.com/api.php/provide/vod",
      "type": 2,
      "isActive": 1,
      "time": "2026-07-05T08:40:14.168Z",
      "isDefault": 0,
      "remark": "speed:82ms",
      "tags": [],
      "priority": 0,
      "proxyMode": "none",
      "customProxy": ""
    },
    {
      "id": "26e9b747-c576-473f-a9d2-38524d35184c",
      "key": "U酷资源88",
      "name": "U酷资源88",
      "api": "https://api.ukuapi88.com/api.php/provide/vod",
      "type": 2,
      "isActive": 1,
      "time": "2026-07-05T08:40:14.168Z",
      "isDefault": 0,
      "remark": "speed:106ms",
      "tags": [],
      "priority": 0,
      "proxyMode": "none",
      "customProxy": ""
    },
    {
      "id": "7c1a3411-443c-40f9-b1a4-76f8a3baeef2",
      "key": "光速资源",
      "name": "光速资源",
      "api": "https://api.guangsuapi.com/api.php/provide/vod",
      "type": 2,
      "isActive": 1,
      "time": "2026-07-05T08:40:14.168Z",
      "isDefault": 0,
      "remark": "speed:117ms",
      "tags": [],
      "priority": 0,
      "proxyMode": "none",
      "customProxy": ""
    },
    {
      "id": "8a74d1e4-aed9-43ea-ae63-3b484fe3edae",
      "key": "百度云资源",
      "name": "百度云资源",
      "api": "https://api.apibdzy.com/api.php/provide/vod",
      "type": 2,
      "isActive": 1,
      "time": "2026-07-05T08:40:14.168Z",
      "isDefault": 0,
      "remark": "speed:118ms",
      "tags": [],
      "priority": 0,
      "proxyMode": "none",
      "customProxy": ""
    },
    {
      "id": "6c6e9011-7759-44ae-9314-685c7716847b",
      "key": "极速资源",
      "name": "极速资源",
      "api": "https://jszyapi.com/api.php/provide/vod",
      "type": 2,
      "isActive": 1,
      "time": "2026-07-05T08:40:14.168Z",
      "isDefault": 0,
      "remark": "speed:124ms",
      "tags": [],
      "priority": 0,
      "proxyMode": "none",
      "customProxy": ""
    },
    {
      "id": "35071f61-28d6-4541-b7cc-9c277e5e0804",
      "key": "最大资源",
      "name": "最大资源",
      "api": "https://api.zuidapi.com/api.php/provide/vod",
      "type": 2,
      "isActive": 1,
      "time": "2026-07-05T08:40:14.168Z",
      "isDefault": 0,
      "remark": "speed:125ms",
      "tags": [],
      "priority": 0,
      "proxyMode": "none",
      "customProxy": ""
    },
    {
      "id": "10c823da-10eb-49db-8cf1-6d7db6dcf1f5",
      "key": "jkun",
      "name": "jkun",
      "api": "https://jkunzyapi.com/api.php/provide/vod",
      "type": 2,
      "isActive": 1,
      "time": "2026-07-05T08:40:14.168Z",
      "isDefault": 0,
      "remark": "speed:129ms",
      "tags": [],
      "priority": 0,
      "proxyMode": "none",
      "customProxy": ""
    },
    {
      "id": "13b8e0de-e3cf-4de5-8110-320a5bfcf72b",
      "key": "黄色仓库",
      "name": "黄色仓库",
      "api": "https://hsckzy.vip/api.php/provide/vod",
      "type": 2,
      "isActive": 1,
      "time": "2026-07-05T08:40:14.168Z",
      "isDefault": 0,
      "remark": "speed:145ms",
      "tags": [],
      "priority": 0,
      "proxyMode": "none",
      "customProxy": ""
    },
    {
      "id": "c408594c-8bf9-4596-8cfe-9514e4b327a8",
      "key": "乐子HTTP",
      "name": "乐子HTTP",
      "api": "http://cj.lziapi.com/api.php/provide/vod",
      "type": 2,
      "isActive": 1,
      "time": "2026-07-05T08:40:14.168Z",
      "isDefault": 0,
      "remark": "speed:160ms",
      "tags": [],
      "priority": 0,
      "proxyMode": "none",
      "customProxy": ""
    },
    {
      "id": "b4fd68b5-2b8d-4f14-8ece-bbc905ff8368",
      "key": "lsb",
      "name": "lsb",
      "api": "https://apilsbzy1.com/api.php/provide/vod",
      "type": 2,
      "isActive": 1,
      "time": "2026-07-05T08:40:14.168Z",
      "isDefault": 0,
      "remark": "speed:160ms",
      "tags": [],
      "priority": 0,
      "proxyMode": "none",
      "customProxy": ""
    },
    {
      "id": "e0ee6d8d-adb5-42fb-a98a-f9abd9a9b063",
      "key": "新浪HTTPS",
      "name": "新浪HTTPS",
      "api": "https://api.xinlangapi.com/xinlangapi.php/provide/vod",
      "type": 2,
      "isActive": 1,
      "time": "2026-07-05T08:40:14.168Z",
      "isDefault": 0,
      "remark": "speed:162ms",
      "tags": [],
      "priority": 0,
      "proxyMode": "none",
      "customProxy": ""
    },
    {
      "id": "dae8e715-b991-476b-b9f5-16c921cb7540",
      "key": "🎧全网┃音乐",
      "name": "🎧全网┃音乐",
      "api": "https://16409.kstore.vip/js/%E5%93%94%E5%93%A9MTV.json",
      "type": 2,
      "isActive": 1,
      "time": "2026-07-05T08:40:14.168Z",
      "isDefault": 0,
      "remark": "speed:174ms",
      "tags": [],
      "priority": 0,
      "proxyMode": "none",
      "customProxy": ""
    },
    {
      "id": "0677381c-5347-4961-9899-b9d39e62eb95",
      "key": "虎牙资源",
      "name": "虎牙资源",
      "api": "https://www.huyaapi.com/api.php/provide/vod",
      "type": 2,
      "isActive": 1,
      "time": "2026-07-05T08:40:14.168Z",
      "isDefault": 0,
      "remark": "speed:193ms",
      "tags": [],
      "priority": 0,
      "proxyMode": "none",
      "customProxy": ""
    },
    {
      "id": "dd81b8bd-e982-4bb0-b40a-569549d20ae8",
      "key": "鲸鱼资源",
      "name": "鲸鱼资源",
      "api": "https://jyzyapi.com/provide/vod",
      "type": 2,
      "isActive": 1,
      "time": "2026-07-05T08:40:14.168Z",
      "isDefault": 0,
      "remark": "speed:196ms",
      "tags": [],
      "priority": 0,
      "proxyMode": "none",
      "customProxy": ""
    },
    {
      "id": "2e55f306-b6c3-4949-b92b-1ee26dbe08d8",
      "key": "🫧韩剧┃蓝光",
      "name": "🫧韩剧┃蓝光",
      "api": "https://16409.kstore.vip/js/hanjukan.json",
      "type": 2,
      "isActive": 1,
      "time": "2026-07-05T08:40:14.168Z",
      "isDefault": 0,
      "remark": "speed:204ms",
      "tags": [],
      "priority": 0,
      "proxyMode": "none",
      "customProxy": ""
    },
    {
      "id": "89f8adf9-5b79-49c3-b331-f6e53e44e4f0",
      "key": "暴风APP",
      "name": "暴风APP",
      "api": "https://app.bfzyapi.com/api.php/provide/vod",
      "type": 2,
      "isActive": 1,
      "time": "2026-07-05T08:40:14.168Z",
      "isDefault": 0,
      "remark": "speed:205ms",
      "tags": [],
      "priority": 0,
      "proxyMode": "none",
      "customProxy": ""
    },
    {
      "id": "a524fcf1-6b06-4032-a0e1-0351583cfd18",
      "key": "天涯资源",
      "name": "天涯资源",
      "api": "https://tyyszy.com/api.php/provide/vod",
      "type": 2,
      "isActive": 1,
      "time": "2026-07-05T08:40:14.168Z",
      "isDefault": 0,
      "remark": "speed:212ms",
      "tags": [],
      "priority": 0,
      "proxyMode": "none",
      "customProxy": ""
    },
    {
      "id": "413a8de2-dc73-4d7f-9851-70f906a2e263",
      "key": "CK",
      "name": "CK",
      "api": "https://www.ckzy1.com/api.php/provide/vod",
      "type": 2,
      "isActive": 1,
      "time": "2026-07-05T08:40:14.168Z",
      "isDefault": 0,
      "remark": "speed:223ms",
      "tags": [],
      "priority": 0,
      "proxyMode": "none",
      "customProxy": ""
    },
    {
      "id": "302320b7-ab64-4b6f-a99b-a398d600d7ac",
      "key": "最大点播",
      "name": "最大点播",
      "api": "http://zuidazy.me/api.php/provide/vod",
      "type": 2,
      "isActive": 1,
      "time": "2026-07-05T08:40:14.168Z",
      "isDefault": 0,
      "remark": "speed:228ms",
      "tags": [],
      "priority": 0,
      "proxyMode": "none",
      "customProxy": ""
    },
    {
      "id": "fab68b77-3547-4c64-88a1-48f2027a4a32",
      "key": "新浪资源",
      "name": "新浪资源",
      "api": "http://api.xinlangapi.com/xinlangapi.php/provide/vod",
      "type": 2,
      "isActive": 1,
      "time": "2026-07-05T08:40:14.168Z",
      "isDefault": 0,
      "remark": "speed:236ms",
      "tags": [],
      "priority": 0,
      "proxyMode": "none",
      "customProxy": ""
    },
    {
      "id": "16ce043c-7b8b-48f0-af9b-113cf28b43db",
      "key": "无尽NET",
      "name": "无尽NET",
      "api": "https://api.wujinapi.net/api.php/provide/vod",
      "type": 2,
      "isActive": 1,
      "time": "2026-07-05T08:40:14.168Z",
      "isDefault": 0,
      "remark": "speed:236ms",
      "tags": [],
      "priority": 0,
      "proxyMode": "none",
      "customProxy": ""
    },
    {
      "id": "0adbc9dc-8d94-4066-8d72-dcb04cffc457",
      "key": "丫丫点播",
      "name": "丫丫点播",
      "api": "https://cj.yayazy.net/api.php/provide/vod",
      "type": 2,
      "isActive": 1,
      "time": "2026-07-05T08:40:14.168Z",
      "isDefault": 0,
      "remark": "speed:241ms",
      "tags": [],
      "priority": 0,
      "proxyMode": "none",
      "customProxy": ""
    },
    {
      "id": "ae55642f-50c0-4bf1-8a83-c7fba8d0fb8b",
      "key": "暴风资源",
      "name": "暴风资源",
      "api": "https://bfzyapi.com/api.php/provide/vod",
      "type": 2,
      "isActive": 1,
      "time": "2026-07-05T08:40:14.168Z",
      "isDefault": 0,
      "remark": "speed:259ms",
      "tags": [],
      "priority": 0,
      "proxyMode": "none",
      "customProxy": ""
    },
    {
      "id": "06d58e8a-cc6b-42e9-a617-49302c4e3564",
      "key": "天涯海角",
      "name": "天涯海角",
      "api": "https://tyyszyapi.com/api.php/provide/vod",
      "type": 2,
      "isActive": 1,
      "time": "2026-07-05T08:40:14.168Z",
      "isDefault": 0,
      "remark": "speed:269ms",
      "tags": [],
      "priority": 0,
      "proxyMode": "none",
      "customProxy": ""
    },
    {
      "id": "97c11df4-43bd-4f51-af7c-1f196f76bcff",
      "key": "无尽CC",
      "name": "无尽CC",
      "api": "https://api.wujinapi.cc/api.php/provide/vod",
      "type": 2,
      "isActive": 1,
      "time": "2026-07-05T08:40:14.168Z",
      "isDefault": 0,
      "remark": "speed:273ms",
      "tags": [],
      "priority": 0,
      "proxyMode": "none",
      "customProxy": ""
    },
    {
      "id": "46447b82-f4bd-4cfd-98d9-5c6ea9160bf3",
      "key": "海豚资源",
      "name": "海豚资源",
      "api": "https://hhzyapi.com/api.php/provide/vod",
      "type": 2,
      "isActive": 1,
      "time": "2026-07-05T08:40:14.168Z",
      "isDefault": 0,
      "remark": "speed:287ms",
      "tags": [],
      "priority": 0,
      "proxyMode": "none",
      "customProxy": ""
    },
    {
      "id": "8f9febba-4c69-4f70-97fe-5bd6716798c9",
      "key": "百万资源",
      "name": "百万资源",
      "api": "https://api.bwzyz.com/api.php/provide/vod",
      "type": 2,
      "isActive": 1,
      "time": "2026-07-05T08:40:14.168Z",
      "isDefault": 0,
      "remark": "speed:291ms",
      "tags": [],
      "priority": 0,
      "proxyMode": "none",
      "customProxy": ""
    },
    {
      "id": "3b102e1e-b125-49d3-bcb2-362791b38457",
      "key": "閃電资源",
      "name": "閃電资源",
      "api": "https://sdzyapi.com/api.php/provide/vod",
      "type": 2,
      "isActive": 1,
      "time": "2026-07-05T08:40:14.168Z",
      "isDefault": 0,
      "remark": "speed:296ms",
      "tags": [],
      "priority": 0,
      "proxyMode": "none",
      "customProxy": ""
    },
    {
      "id": "1ee82f9a-e11f-4ed3-a7c3-37721a3fae1a",
      "key": "红牛资源",
      "name": "红牛资源",
      "api": "https://www.hongniuzy2.com/api.php/provide/vod",
      "type": 2,
      "isActive": 1,
      "time": "2026-07-05T08:40:14.168Z",
      "isDefault": 0,
      "remark": "speed:297ms",
      "tags": [],
      "priority": 0,
      "proxyMode": "none",
      "customProxy": ""
    },
    {
      "id": "7bb1adc9-c91e-4f7c-8f2c-5f23516df13e",
      "key": "黄AV资源站",
      "name": "黄AV资源站",
      "api": "https://www.pgxdy.com/api/json.php",
      "type": 2,
      "isActive": 1,
      "time": "2026-07-05T08:40:14.168Z",
      "isDefault": 0,
      "remark": "speed:317ms",
      "tags": [],
      "priority": 0,
      "proxyMode": "none",
      "customProxy": ""
    },
    {
      "id": "a99a0ff2-3300-430d-b169-dd114d93d981",
      "key": "索尼-闪电",
      "name": "索尼-闪电",
      "api": "https://xsd.sdzyapi.com/api.php/provide/vod",
      "type": 2,
      "isActive": 1,
      "time": "2026-07-05T08:40:14.168Z",
      "isDefault": 0,
      "remark": "speed:322ms",
      "tags": [],
      "priority": 0,
      "proxyMode": "none",
      "customProxy": ""
    },
    {
      "id": "fdda6b78-8e33-4590-93a5-d3ad766390a4",
      "key": "小鸡资源",
      "name": "小鸡资源",
      "api": "https://api.xiaojizy.live/provide/vod",
      "type": 2,
      "isActive": 1,
      "time": "2026-07-05T08:40:14.168Z",
      "isDefault": 0,
      "remark": "speed:326ms",
      "tags": [],
      "priority": 0,
      "proxyMode": "none",
      "customProxy": ""
    },
    {
      "id": "a9910e4b-15e0-4c61-b034-1b9339c1ba1c",
      "key": "樱花资源",
      "name": "樱花资源",
      "api": "https://m3u8.apiyhzy.com/api.php/provide/vod",
      "type": 2,
      "isActive": 1,
      "time": "2026-07-05T08:40:14.168Z",
      "isDefault": 0,
      "remark": "speed:328ms",
      "tags": [],
      "priority": 0,
      "proxyMode": "none",
      "customProxy": ""
    },
    {
      "id": "afe7ced0-8537-4302-af3a-44fac4338b35",
      "key": "玉兔",
      "name": "玉兔",
      "api": "https://yutuzy10.com/api.php/provide/vod",
      "type": 2,
      "isActive": 1,
      "time": "2026-07-05T08:40:14.168Z",
      "isDefault": 0,
      "remark": "speed:344ms",
      "tags": [],
      "priority": 0,
      "proxyMode": "none",
      "customProxy": ""
    },
    {
      "id": "49dbe016-ce3c-4499-8227-a94b0d669fad",
      "key": "牛牛点播",
      "name": "牛牛点播",
      "api": "https://api.niuniuzy.me/api.php/provide/vod",
      "type": 2,
      "isActive": 1,
      "time": "2026-07-05T08:40:14.168Z",
      "isDefault": 0,
      "remark": "speed:365ms",
      "tags": [],
      "priority": 0,
      "proxyMode": "none",
      "customProxy": ""
    },
    {
      "id": "a10a20e3-35fa-4b4f-81c9-aca3b0ff22ca",
      "key": "红牛资源3",
      "name": "红牛资源3",
      "api": "https://www.hongniuzy3.com/api.php/provide/vod",
      "type": 2,
      "isActive": 1,
      "time": "2026-07-05T08:40:14.168Z",
      "isDefault": 0,
      "remark": "speed:368ms",
      "tags": [],
      "priority": 0,
      "proxyMode": "none",
      "customProxy": ""
    },
    {
      "id": "d87c5351-d166-4e30-ae0d-fa5b29316836",
      "key": "乐播资源",
      "name": "乐播资源",
      "api": "https://lbapi9.com/api.php/provide/vod",
      "type": 2,
      "isActive": 1,
      "time": "2026-07-05T08:40:14.168Z",
      "isDefault": 0,
      "remark": "speed:373ms",
      "tags": [],
      "priority": 0,
      "proxyMode": "none",
      "customProxy": ""
    },
    {
      "id": "2dfc98e3-199c-41f5-a931-e9cf2e456b48",
      "key": "美少女资源站",
      "name": "美少女资源站",
      "api": "https://www.msnii.com/api/json.php",
      "type": 2,
      "isActive": 1,
      "time": "2026-07-05T08:40:14.168Z",
      "isDefault": 0,
      "remark": "speed:378ms",
      "tags": [],
      "priority": 0,
      "proxyMode": "none",
      "customProxy": ""
    },
    {
      "id": "f05e9cf8-75d1-485a-8d63-f9f4ddb12a05",
      "key": "乐子资源",
      "name": "乐子资源",
      "api": "https://cj.lziapi.com/api.php/provide/vod",
      "type": 2,
      "isActive": 1,
      "time": "2026-07-05T08:40:14.168Z",
      "isDefault": 0,
      "remark": "speed:384ms",
      "tags": [],
      "priority": 0,
      "proxyMode": "none",
      "customProxy": ""
    },
    {
      "id": "694fb14d-f9b1-48a8-bf51-fd2f65bb5cf2",
      "key": "速博资源",
      "name": "速博资源",
      "api": "https://subocaiji.com/api.php/provide/vod",
      "type": 2,
      "isActive": 1,
      "time": "2026-07-05T08:40:14.168Z",
      "isDefault": 0,
      "remark": "speed:390ms",
      "tags": [],
      "priority": 0,
      "proxyMode": "none",
      "customProxy": ""
    },
    {
      "id": "90b27d70-3a48-4507-9dff-3bf19254e460",
      "key": "优酷资源",
      "name": "优酷资源",
      "api": "https://api.ukuapi.com/api.php/provide/vod",
      "type": 2,
      "isActive": 1,
      "time": "2026-07-05T08:40:14.168Z",
      "isDefault": 0,
      "remark": "speed:393ms",
      "tags": [],
      "priority": 0,
      "proxyMode": "none",
      "customProxy": ""
    },
    {
      "id": "685d767f-cee9-4d10-b2fb-4f7415db0820",
      "key": "细胞采集",
      "name": "细胞采集",
      "api": "https://www.xxibaozyw.com/api.php/provide/vod",
      "type": 2,
      "isActive": 1,
      "time": "2026-07-05T08:40:14.168Z",
      "isDefault": 0,
      "remark": "speed:411ms",
      "tags": [],
      "priority": 0,
      "proxyMode": "none",
      "customProxy": ""
    },
    {
      "id": "5ef300ac-5d66-4ad9-9c70-5a4b497e8d0e",
      "key": "飘零资源",
      "name": "飘零资源",
      "api": "https://p2100.net/api.php/provide/vod",
      "type": 2,
      "isActive": 1,
      "time": "2026-07-05T08:40:14.168Z",
      "isDefault": 0,
      "remark": "speed:430ms",
      "tags": [],
      "priority": 0,
      "proxyMode": "none",
      "customProxy": ""
    },
    {
      "id": "21fad495-576a-4f01-9c89-219a20c80cde",
      "key": "淫水机资源站",
      "name": "淫水机资源站",
      "api": "https://www.xrbsp.com/api/json.php",
      "type": 2,
      "isActive": 1,
      "time": "2026-07-05T08:40:14.168Z",
      "isDefault": 0,
      "remark": "speed:435ms",
      "tags": [],
      "priority": 0,
      "proxyMode": "none",
      "customProxy": ""
    },
    {
      "id": "15efcdb4-2af9-4dbf-a482-3595fd630a46",
      "key": "香奶儿资源站",
      "name": "香奶儿资源站",
      "api": "https://www.gdlsp.com/api/json.php",
      "type": 2,
      "isActive": 1,
      "time": "2026-07-05T08:40:14.168Z",
      "isDefault": 0,
      "remark": "speed:436ms",
      "tags": [],
      "priority": 0,
      "proxyMode": "none",
      "customProxy": ""
    },
    {
      "id": "6f78ffbb-c5d8-4b27-9f44-7fb03d051223",
      "key": "iKun资源",
      "name": "iKun资源",
      "api": "https://ikunzyapi.com/api.php/provide/vod",
      "type": 2,
      "isActive": 1,
      "time": "2026-07-05T08:40:14.168Z",
      "isDefault": 0,
      "remark": "speed:459ms",
      "tags": [],
      "priority": 0,
      "proxyMode": "none",
      "customProxy": ""
    },
    {
      "id": "a4c9bcdb-3cbf-45b0-9555-1d46d86a2361",
      "key": "白嫖资源站",
      "name": "白嫖资源站",
      "api": "https://www.kxgav.com/api/json.php",
      "type": 2,
      "isActive": 1,
      "time": "2026-07-05T08:40:14.168Z",
      "isDefault": 0,
      "remark": "speed:464ms",
      "tags": [],
      "priority": 0,
      "proxyMode": "none",
      "customProxy": ""
    },
    {
      "id": "57ba0bd9-51ef-4b99-91f9-1af4bacce5f8",
      "key": "非凡采集HTTPS",
      "name": "非凡采集HTTPS",
      "api": "https://cj.ffzyapi.com/api.php/provide/vod",
      "type": 2,
      "isActive": 1,
      "time": "2026-07-05T08:40:14.168Z",
      "isDefault": 0,
      "remark": "speed:474ms",
      "tags": [],
      "priority": 0,
      "proxyMode": "none",
      "customProxy": ""
    },
    {
      "id": "e5be6972-ae5c-458d-8de9-fafc9966ebfc",
      "key": "🥅企鹅┃体育直播",
      "name": "🥅企鹅┃体育直播",
      "api": "https://16409.kstore.vip/js/%E4%BC%81%E9%B9%85%E7%9B%B4%E6%92%AD.json",
      "type": 2,
      "isActive": 1,
      "time": "2026-07-05T08:40:14.168Z",
      "isDefault": 0,
      "remark": "speed:503ms",
      "tags": [],
      "priority": 0,
      "proxyMode": "none",
      "customProxy": ""
    },
    {
      "id": "a2ed7b62-33ce-475f-9b46-7b947219980b",
      "key": "旺旺API",
      "name": "旺旺API",
      "api": "https://api.wwzy.tv/api.php/provide/vod",
      "type": 2,
      "isActive": 1,
      "time": "2026-07-05T08:40:14.168Z",
      "isDefault": 0,
      "remark": "speed:523ms",
      "tags": [],
      "priority": 0,
      "proxyMode": "none",
      "customProxy": ""
    },
    {
      "id": "1f9bbf55-0ba9-40b4-8030-619428a9ecaf",
      "key": "番号资源",
      "name": "番号资源",
      "api": "http://fhapi9.com/api.php/provide/vod",
      "type": 2,
      "isActive": 1,
      "time": "2026-07-05T08:40:14.168Z",
      "isDefault": 0,
      "remark": "speed:526ms",
      "tags": [],
      "priority": 0,
      "proxyMode": "none",
      "customProxy": ""
    },
    {
      "id": "73d1c9fd-5dd4-483e-be98-87a054d2b012",
      "key": "卧龙采集",
      "name": "卧龙采集",
      "api": "https://collect.wolongzyw.com/api.php/provide/vod",
      "type": 2,
      "isActive": 1,
      "time": "2026-07-05T08:40:14.168Z",
      "isDefault": 0,
      "remark": "speed:550ms",
      "tags": [],
      "priority": 0,
      "proxyMode": "none",
      "customProxy": ""
    },
    {
      "id": "bade7306-6255-4df1-bd4f-6dc902bd2a6f",
      "key": "旺旺资源",
      "name": "旺旺资源",
      "api": "https://wwzy.tv/api.php/provide/vod",
      "type": 2,
      "isActive": 1,
      "time": "2026-07-05T08:40:14.168Z",
      "isDefault": 0,
      "remark": "speed:552ms",
      "tags": [],
      "priority": 0,
      "proxyMode": "none",
      "customProxy": ""
    },
    {
      "id": "a39dcd7b-2919-4772-8dd7-a799561a2e97",
      "key": "卧龙资源",
      "name": "卧龙资源",
      "api": "https://wolongzyw.com/api.php/provide/vod",
      "type": 2,
      "isActive": 1,
      "time": "2026-07-05T08:40:14.168Z",
      "isDefault": 0,
      "remark": "speed:557ms",
      "tags": [],
      "priority": 0,
      "proxyMode": "none",
      "customProxy": ""
    },
    {
      "id": "6652818b-0966-4abf-837c-bf8eebe0532b",
      "key": "茅台资源",
      "name": "茅台资源",
      "api": "https://caiji.maotaizy.cc/api.php/provide/vod",
      "type": 2,
      "isActive": 1,
      "time": "2026-07-05T08:40:14.168Z",
      "isDefault": 0,
      "remark": "speed:612ms",
      "tags": [],
      "priority": 0,
      "proxyMode": "none",
      "customProxy": ""
    },
    {
      "id": "e4286fb5-7399-48c3-8991-c0eb83ef0c6e",
      "key": "精品资源",
      "name": "精品资源",
      "api": "https://www.jingpinx.com/api.php/provide/vod",
      "type": 2,
      "isActive": 1,
      "time": "2026-07-05T08:40:14.168Z",
      "isDefault": 0,
      "remark": "speed:613ms",
      "tags": [],
      "priority": 0,
      "proxyMode": "none",
      "customProxy": ""
    },
    {
      "id": "e6864ef3-b4f0-4384-b96b-194d94df822e",
      "key": "🧲磁力在线┃原盘",
      "name": "🧲磁力在线┃原盘",
      "api": "https://16409.kstore.vip/js/dyg.json",
      "type": 2,
      "isActive": 1,
      "time": "2026-07-05T08:40:14.168Z",
      "isDefault": 0,
      "remark": "speed:621ms",
      "tags": [],
      "priority": 0,
      "proxyMode": "none",
      "customProxy": ""
    },
    {
      "id": "a6690a3b-ad1a-42fc-87c8-16aceb8d9a01",
      "key": "非凡线路1",
      "name": "非凡线路1",
      "api": "http://ffzy1.tv/api.php/provide/vod",
      "type": 2,
      "isActive": 1,
      "time": "2026-07-05T08:40:14.168Z",
      "isDefault": 0,
      "remark": "speed:632ms",
      "tags": [],
      "priority": 0,
      "proxyMode": "none",
      "customProxy": ""
    },
    {
      "id": "2f7fb434-07c5-4a11-99a9-00b011058c86",
      "key": "豆瓣资源",
      "name": "豆瓣资源",
      "api": "https://dbzy.tv/api.php/provide/vod",
      "type": 2,
      "isActive": 1,
      "time": "2026-07-05T08:40:14.168Z",
      "isDefault": 0,
      "remark": "speed:650ms",
      "tags": [],
      "priority": 0,
      "proxyMode": "none",
      "customProxy": ""
    },
    {
      "id": "90a20f9c-c966-4f14-b636-9f26ebb943e6",
      "key": "后台发送接口2字获取最新",
      "name": "后台发送接口2字获取最新",
      "api": "https://mk1080.top/get.txt",
      "type": 2,
      "isActive": 1,
      "time": "2026-07-05T08:40:14.168Z",
      "isDefault": 0,
      "remark": "speed:664ms",
      "tags": [],
      "priority": 0,
      "proxyMode": "none",
      "customProxy": ""
    },
    {
      "id": "61d95364-fcae-4683-831c-1fd5ddec3476",
      "key": "🪔聚合┃短剧",
      "name": "🪔聚合┃短剧",
      "api": "https://16409.kstore.vip/js/%E8%81%9A%E5%90%88%E7%9F%AD%E5%89%A7.js",
      "type": 2,
      "isActive": 1,
      "time": "2026-07-05T08:40:14.168Z",
      "isDefault": 0,
      "remark": "speed:702ms",
      "tags": [],
      "priority": 0,
      "proxyMode": "none",
      "customProxy": ""
    },
    {
      "id": "146cf2b6-bf00-410d-a7aa-a68cd4ce4377",
      "key": "91麻豆",
      "name": "91麻豆",
      "api": "https://91md.me/api.php/provide/vod",
      "type": 2,
      "isActive": 1,
      "time": "2026-07-05T08:40:14.168Z",
      "isDefault": 0,
      "remark": "speed:876ms",
      "tags": [],
      "priority": 0,
      "proxyMode": "none",
      "customProxy": ""
    },
    {
      "id": "f3c4d8e8-1002-461e-9547-a74c332dafe5",
      "key": "非凡采集",
      "name": "非凡采集",
      "api": "http://cj.ffzyapi.com/api.php/provide/vod",
      "type": 2,
      "isActive": 1,
      "time": "2026-07-05T08:40:14.168Z",
      "isDefault": 0,
      "remark": "speed:922ms",
      "tags": [],
      "priority": 0,
      "proxyMode": "none",
      "customProxy": ""
    },
    {
      "id": "0c36f824-e31f-442f-a02d-4342c61cde82",
      "key": "非凡资源",
      "name": "非凡资源",
      "api": "http://ffzy5.tv/api.php/provide/vod",
      "type": 2,
      "isActive": 1,
      "time": "2026-07-05T08:40:14.168Z",
      "isDefault": 0,
      "remark": "speed:1076ms",
      "tags": [],
      "priority": 0,
      "proxyMode": "none",
      "customProxy": ""
    },
    {
      "id": "2f9c9735-d45b-414a-ab61-75cab01b5ab2",
      "key": "森林资源",
      "name": "森林资源",
      "api": "https://slapibf.com/api.php/provide/vod",
      "type": 2,
      "isActive": 1,
      "time": "2026-07-05T08:40:14.168Z",
      "isDefault": 0,
      "remark": "speed:1208ms",
      "tags": [],
      "priority": 0,
      "proxyMode": "none",
      "customProxy": ""
    },
    {
      "id": "8f18191c-8607-433e-a3ae-d47185ff0e36",
      "key": "魔都资源",
      "name": "魔都资源",
      "api": "https://www.mdzyapi.com/api.php/provide/vod",
      "type": 2,
      "isActive": 1,
      "time": "2026-07-05T08:40:14.168Z",
      "isDefault": 0,
      "remark": "speed:1223ms",
      "tags": [],
      "priority": 0,
      "proxyMode": "none",
      "customProxy": ""
    },
    {
      "id": "9fde7108-c071-4d07-b0e8-11a6e3e9ba92",
      "key": "魔都动漫",
      "name": "魔都动漫",
      "api": "https://caiji.moduapi.cc/api.php/provide/vod",
      "type": 2,
      "isActive": 1,
      "time": "2026-07-05T08:40:14.168Z",
      "isDefault": 0,
      "remark": "speed:1350ms",
      "tags": [],
      "priority": 0,
      "proxyMode": "none",
      "customProxy": ""
    },
    {
      "id": "29ba77a3-4d4c-4ae1-b2d9-9600b451b21d",
      "key": "奶香香",
      "name": "奶香香",
      "api": "https://Naixxzy.com/api.php/provide/vod",
      "type": 2,
      "isActive": 1,
      "time": "2026-07-05T08:40:14.168Z",
      "isDefault": 0,
      "remark": "speed:1388ms",
      "tags": [],
      "priority": 0,
      "proxyMode": "none",
      "customProxy": ""
    },
    {
      "id": "f9e8b209-ccc4-4559-a23c-c6bf858def66",
      "key": "1080JSON",
      "name": "1080JSON",
      "api": "https://api.1080zyku.com/inc/apijson.php",
      "type": 2,
      "isActive": 1,
      "time": "2026-07-05T08:40:14.168Z",
      "isDefault": 0,
      "remark": "speed:1465ms",
      "tags": [],
      "priority": 0,
      "proxyMode": "none",
      "customProxy": ""
    },
    {
      "id": "aad43a58-9cdd-49f4-9eb8-3ee998721098",
      "key": "奥斯卡资源",
      "name": "奥斯卡资源",
      "api": "https://aosikazy.com/api.php/provide/vod",
      "type": 2,
      "isActive": 1,
      "time": "2026-07-05T08:40:14.168Z",
      "isDefault": 0,
      "remark": "speed:1482ms",
      "tags": [],
      "priority": 0,
      "proxyMode": "none",
      "customProxy": ""
    },
    {
      "id": "cc0fbb40-ef47-40ec-8906-15f520b05e1f",
      "key": "如意资源",
      "name": "如意资源",
      "api": "https://cj.rycjapi.com/api.php/provide/vod",
      "type": 2,
      "isActive": 1,
      "time": "2026-07-05T08:40:14.168Z",
      "isDefault": 0,
      "remark": "speed:1578ms",
      "tags": [],
      "priority": 0,
      "proxyMode": "none",
      "customProxy": ""
    },
    {
      "id": "b47a8946-ffcc-4723-af01-dda54985e18f",
      "key": "电影天堂",
      "name": "电影天堂",
      "api": "http://caiji.dyttzyapi.com/api.php/provide/vod",
      "type": 2,
      "isActive": 1,
      "time": "2026-07-05T08:40:14.168Z",
      "isDefault": 0,
      "remark": "speed:1618ms",
      "tags": [],
      "priority": 0,
      "proxyMode": "none",
      "customProxy": ""
    },
    {
      "id": "a05dd2e3-3514-4c06-ae6b-ab94852a80b6",
      "key": "360资源",
      "name": "360资源",
      "api": "https://360zy.com/api.php/provide/vod",
      "type": 2,
      "isActive": 1,
      "time": "2026-07-05T08:40:14.168Z",
      "isDefault": 0,
      "remark": "speed:1748ms",
      "tags": [],
      "priority": 0,
      "proxyMode": "none",
      "customProxy": ""
    },
    {
      "id": "bd2f3816-de28-45ec-97e1-0ab81cf00b55",
      "key": "非凡API",
      "name": "非凡API",
      "api": "https://api.ffzyapi.com/api.php/provide/vod",
      "type": 2,
      "isActive": 1,
      "time": "2026-07-05T08:40:14.168Z",
      "isDefault": 0,
      "remark": "speed:1887ms",
      "tags": [],
      "priority": 0,
      "proxyMode": "none",
      "customProxy": ""
    },
    {
      "id": "e45221b0-4fc1-4e78-9eb1-f053ff2b307c",
      "key": "魔都影视",
      "name": "魔都影视",
      "api": "https://www.moduzy.com/api.php/provide/vod",
      "type": 2,
      "isActive": 1,
      "time": "2026-07-05T08:40:14.168Z",
      "isDefault": 0,
      "remark": "speed:1911ms",
      "tags": [],
      "priority": 0,
      "proxyMode": "none",
      "customProxy": ""
    },
    {
      "id": "4ed8e7d0-bad9-44d2-b931-df648a2abe96",
      "key": "鲨鱼资源",
      "name": "鲨鱼资源",
      "api": "https://shayuapi.com/api.php/provide/vod",
      "type": 2,
      "isActive": 1,
      "time": "2026-07-05T08:40:14.168Z",
      "isDefault": 0,
      "remark": "speed:2060ms",
      "tags": [],
      "priority": 0,
      "proxyMode": "none",
      "customProxy": ""
    }
  ]
}